avishan_wrapper_old/__init__.py
avishan_wrapper_old/middlewares.py
avishan_wrapper_old-0.1.0.dist-info/LICENSE
avishan_wrapper_old-0.1.0.dist-info/METADATA
avishan_wrapper_old-0.1.0.dist-info/WHEEL
avishan_wrapper_old-0.1.0.dist-info/top_level.txt
avishan_wrapper_old-0.1.0.dist-info/RECORD
